steamsync/__init__.py
steamsync/defs.py
steamsync/launchers/__init__.py
steamsync/launchers/egs.py
steamsync/launchers/itch.py
steamsync/launchers/launcher.py
steamsync/launchers/legendary.py
steamsync/launchers/static/list_xbox_games.ps1
steamsync/launchers/xbox.py
steamsync/steameditor.py
steamsync/steamsync.py
steamsync/util.py
steamsync-0.4.2.dist-info/entry_points.txt
steamsync-0.4.2.dist-info/METADATA
steamsync-0.4.2.dist-info/WHEEL
steamsync-0.4.2.dist-info/RECORD
